llama_index/readers/metal/__init__.py
llama_index/readers/metal/base.py
llama_index_readers_metal-0.4.1.dist-info/METADATA
llama_index_readers_metal-0.4.1.dist-info/WHEEL
llama_index_readers_metal-0.4.1.dist-info/licenses/LICENSE
llama_index_readers_metal-0.4.1.dist-info/RECORD
