Metadata-Version: 2.4
Name: llama-index-readers-metal
Version: 0.4.1
Summary: llama-index readers metal integration
Author-email: Your Name <you@example.com>
Maintainer: getmetal
License-Expression: MIT
License-File: LICENSE
Keywords: metal,retriever,storage
Requires-Python: <4.0,>=3.9
Requires-Dist: llama-index-core<0.15,>=0.13.0
Requires-Dist: metal-sdk<3,>=2.5.1
